core_lib/__init__.py
core_lib/core_lib_auth/__init__.py
core_lib/core_lib_auth/credentials_service.py
core_lib/core_lib_auth/crypto.py
core_lib/core_lib_bullmq/__init__.py
core_lib/core_lib_bullmq/analytics.py
core_lib/core_lib_bullmq/base_worker.py
core_lib/core_lib_bullmq/bullmq_adapter.py
core_lib/core_lib_bullmq/external_worker_adapter.py
core_lib/core_lib_bullmq/flow_builder.py
core_lib/core_lib_bullmq/job_context.py
core_lib/core_lib_bullmq/queue_manager.py
core_lib/core_lib_bullmq/worker_backend_factory.py
core_lib/core_lib_bullmq/worker_backend_port.py
core_lib/core_lib_config/__init__.py
core_lib/core_lib_config/settings.py
core_lib/core_lib_db/__init__.py
core_lib/core_lib_db/models.py
core_lib/core_lib_db/session.py
core_lib/core_lib_db/session_utils.py
core_lib/core_lib_llm/__init__.py
core_lib/core_lib_llm/llm_port.py
core_lib/core_lib_llm/llm_service.py
core_lib/core_lib_llm/ollama_adapter.py
core_lib/core_lib_llm/openrouter_adapter.py
core_lib/core_lib_monitoring/__init__.py
core_lib/core_lib_monitoring/enriched_metrics.py
core_lib/core_lib_monitoring/llm_pricing.py
core_lib/core_lib_monitoring/resource_metrics.py
core_lib/core_lib_utils/__init__.py
core_lib/core_lib_utils/filesystem.py
core_lib/core_lib_utils/hooks.py
core_lib/core_lib_utils/models.py
core_lib/core_lib_utils/retry.py
core_lib/core_lib_utils/system.py
core_lib_storage/__init__.py
core_lib_storage/base_storage.py
core_lib_storage/s3_storage.py
core_lib_storage/storage_provider_factory.py
worker_core_lib-0.0.47.dist-info/METADATA
worker_core_lib-0.0.47.dist-info/WHEEL
worker_core_lib-0.0.47.dist-info/top_level.txt
worker_core_lib-0.0.47.dist-info/RECORD
