Metadata-Version: 2.4
Name: worker-core-lib
Version: 0.0.47
Summary: Core library for worker services
Author-email: Jordane Masson <masson.jordan@gmail.com>
Project-URL: Homepage, https://github.com/Mesh-Sync/Mesh-Sync
Project-URL: Bug Tracker, https://github.com/Mesh-Sync/Mesh-Sync
Classifier: Programming Language :: Python :: 3
Classifier: License :: OSI Approved :: MIT License
Classifier: Operating System :: OS Independent
Requires-Python: >=3.10
Requires-Dist: pydantic-settings~=2.0.0
Requires-Dist: sqlalchemy~=2.0.0
Requires-Dist: boto3~=1.28.0
Requires-Dist: bullmq<2.16.0,>=2.15.0
Requires-Dist: gdown~=4.7.0
Requires-Dist: google-api-python-client~=2.90.0
Requires-Dist: google-auth-httplib2~=0.1.0
Requires-Dist: google-auth-oauthlib~=1.0.0
Requires-Dist: pysftp~=0.2.9
Requires-Dist: requests~=2.31.0
Requires-Dist: paramiko~=3.3.0
Requires-Dist: cryptography~=41.0.5
Requires-Dist: pytest~=7.4.0
Requires-Dist: pytest-asyncio~=0.21.0
Requires-Dist: pyyaml~=6.0
Requires-Dist: watchfiles~=0.19.0
Requires-Dist: python-dotenv~=1.0.0
Requires-Dist: redis<6.0.0,>=5.0.0
Requires-Dist: psycopg2-binary~=2.9.0
Requires-Dist: Pillow~=10.0.0
Requires-Dist: minio~=7.1.0
Requires-Dist: ffmpeg-python~=0.2.0
Requires-Dist: python-dateutil~=2.8.0
Requires-Dist: pytz~=2023.3
Requires-Dist: mesh-sync-worker-backend-client<5.0.0,>=4.0.0
Requires-Dist: elasticsearch~=8.11.0
Requires-Dist: psutil>=5.9.0
Requires-Dist: httpx>=0.24.0
